starshipagentic/__init__.py
starshipagentic/__main__.py
starshipagentic/cli.py
starshipagentic/cli_generated.py
starshipagentic/cli_static-delete-me.py
starshipagentic/cli_static.py
starshipagentic/commands-list.yml
starshipagentic/starshipagentic.yml
starshipagentic/commands/__init__.py
starshipagentic/commands/captains_orders/__init__.py
starshipagentic/commands/captains_orders/engage/__init__.py
starshipagentic/commands/captains_orders/engage/cli.py
starshipagentic/commands/captains_orders/engage/services.py
starshipagentic/commands/captains_orders/trycoder/__init__.py
starshipagentic/commands/captains_orders/trycoder/cli.py
starshipagentic/commands/captains_orders/trycoder/services.py
starshipagentic/commands/captains_orders/warp_speed/__init__.py
starshipagentic/commands/captains_orders/warp_speed/cli.py
starshipagentic/commands/captains_orders/warp_speed/services.py
starshipagentic/commands/communications_officer/__init__.py
starshipagentic/commands/communications_officer/authorize_codes/__init__.py
starshipagentic/commands/communications_officer/authorize_codes/cli.py
starshipagentic/commands/communications_officer/authorize_codes/services.py
starshipagentic/commands/communications_officer/receive_transmission/__init__.py
starshipagentic/commands/communications_officer/receive_transmission/cli.py
starshipagentic/commands/communications_officer/receive_transmission/services.py
starshipagentic/commands/communications_officer/scan_sector/__init__.py
starshipagentic/commands/communications_officer/scan_sector/cli.py
starshipagentic/commands/communications_officer/scan_sector/services.py
starshipagentic/commands/droids/__init__.py
starshipagentic/commands/droids/droid_splain/__init__.py
starshipagentic/commands/droids/droid_splain/cli.py
starshipagentic/commands/droids/droid_splain/services.py
starshipagentic/commands/droids/man_splain/__init__.py
starshipagentic/commands/droids/man_splain/cli.py
starshipagentic/commands/droids/man_splain/services.py
starshipagentic-0.1.11.dist-info/LICENSE.md
starshipagentic-0.1.11.dist-info/LICENSE_HEADER.txt
starshipagentic-0.1.11.dist-info/METADATA
starshipagentic-0.1.11.dist-info/WHEEL
starshipagentic-0.1.11.dist-info/entry_points.txt
starshipagentic-0.1.11.dist-info/top_level.txt
starshipagentic-0.1.11.dist-info/RECORD
