Metadata-Version: 2.2
Name: starshipagentic
Version: 0.1.11
Summary: AI-assisted software development with a sci-fi inspired interface
Author-email: Travis Somerville and David Samson <starshipagentic@gmail.com>
License: GNU Affero General Public License (AGPL) v3. Note: Code output generated by Starship Agentic is licensed under the MIT License.
Project-URL: Homepage, https://github.com/starshipagentic/pypistarshipagentic
Project-URL: Bug Tracker, https://github.com/starshipagentic/pypistarshipagentic/issues
Project-URL: Website, https://www.starshipagentic.com
Project-URL: Social Media, https://youtube.com/@starshipagentic
Project-URL: Patreon, https://www.patreon.com/c/starshipagentic
Project-URL: Buy Me a Coffee, https://buymeacoffee.com/starshipagentic
Classifier: Programming Language :: Python :: 3
Classifier: Programming Language :: Python :: 3.8
Classifier: Programming Language :: Python :: 3.9
Classifier: Programming Language :: Python :: 3.10
Classifier: License :: OSI Approved :: GNU Affero General Public License v3
Classifier: Operating System :: OS Independent
Classifier: Development Status :: 3 - Alpha
Classifier: Intended Audience :: Developers
Classifier: Topic :: Software Development :: Code Generators
Requires-Python: >=3.8
License-File: LICENSE.md
License-File: LICENSE_HEADER.txt
Requires-Dist: click>=8.0.0
Requires-Dist: rich>=10.0.0
Requires-Dist: requests>=2.25.0
Requires-Dist: tinydb>=4.5.0
Requires-Dist: pygame>=2.0.0
Requires-Dist: pyyaml>=6.0
